ColorfulData_Package/ColorfulData.py
ColorfulData_Package/__init__.py
ColorfulData-1.0.2.dist-info/METADATA
ColorfulData-1.0.2.dist-info/WHEEL
ColorfulData-1.0.2.dist-info/top_level.txt
ColorfulData-1.0.2.dist-info/RECORD
